{
    "loot_table": [
        {"name": "Afanc", "description": "A mythical creature often depicted as a demon crocodile.", "value": 100, "loot_percentage": 1},
        {"name": "Ascallion", "description": "A fierce sea creature, known for its hard shell and sharp teeth.", "value": 150, "loot_percentage": 1},
        {"name": "Barbfish", "description": "A species of freshwater bottom-feeder shark from Amn.", "value": 50, "loot_percentage": 1},
        {"name": "Bichir", "description": "A species of fish known for its elongated body and large scales.", "value": 60, "loot_percentage": 1},
        {"name": "Black Burner", "description": "A fiery fish emitting dark smoke, usually found in volcanic underwater vents.", "value": 200, "loot_percentage": 1},
        {"name": "Bloatfish", "description": "A fish that inflates its body when threatened.", "value": 30, "loot_percentage": 1},
        {"name": "Brownfin", "description": "A species of freshwater fish found in Cormyr and the King's Forest.", "value": 40, "loot_percentage": 1},
        {"name": "Giant Catfish", "description": "A larger version of the common catfish, often found in deep rivers.", "value": 70, "loot_percentage": 1},
        {"name": "Stalking Catfish", "description": "A silent hunter of the underwater world, known for its stealth.", "value": 80, "loot_percentage": 1},
        {"name": "Crystal Nipper", "description": "A small, translucent fish known for its powerful bite.", "value": 120, "loot_percentage": 1},
        {"name": "Dunchow", "description": "A delicacy in Amn only found in Lake Esmel.", "value": 150, "loot_percentage": 1},
        {"name": "Icetail", "description": "A fish adapted to cold environments, with a tail resembling a shard of ice.", "value": 90, "loot_percentage": 1},
        {"name": "Jewelfish", "description": "A beautifully colored fish prized by collectors.", "value": 250, "loot_percentage": 1},
        {"name": "Hetfish", "description": "Swarming fish known for their super-heated bodies that turn water into steam.", "value": 180, "loot_percentage": 1},
        {"name": "Hogfish", "description": "A species of fish found in Akanamere, often dried and stocked in pantries of the city-state of Sumbria.", "value": 50, "loot_percentage": 1},
        {"name": "Manyfin", "description": "A fish with an unusually large number of fins, creating a unique silhouette in the water.", "value": 75, "loot_percentage": 1},
        {"name": "Pike", "description": "A species of big and energetic freshwater predators.", "value": 80, "loot_percentage": 1},
        {"name": "Northern Pike", "description": "A species of big and energetic cold brackish water-dwelling cousins from the Sea of Moving Ice.", "value": 85, "loot_percentage": 1},
        {"name": "Piranha", "description": "Small schooling predators that go into blood frenzy and swarm their prey.", "value": 60, "loot_percentage": 1},
        {"name": "Pyrimo", "description": "A fish species that is well-adapted to high-temperature environments.", "value": 90, "loot_percentage": 1},
        {"name": "Quippers", "description": "Small, carnivorous fish, often moving in large schools.", "value": 30, "loot_percentage": 1},
        {"name": "Greater Raik", "description": "Species of aggressive fish with hooked jaws found in the waters of Sea of Fallen Stars.", "value": 120, "loot_percentage": 1},
        {"name": "Lesser Raik", "description": "Smaller subspecies of Raiks, equally aggressive but not as threatening.", "value": 90, "loot_percentage": 1},
        {"name": "S'repic", "description": "A flesh-eating fish from the Malatran Plateau with huge silver scales.", "value": 200, "loot_percentage": 1},
        {"name": "Salmon", "description": "A common fish species, well-regarded for its taste.", "value": 50, "loot_percentage": 1},
        {"name": "Sardine", "description": "Small silver fish often found in large schools.", "value": 10, "loot_percentage": 1},
        {"name": "Silverling", "description": "Small, silver-colored fish that are quite common in rivers and lakes.", "value": 20, "loot_percentage": 1},
        {"name": "Singing Fish", "description": "Fancifully-cooked festival fish from the Blade Kingdoms, caught in the waters of Akanamere.", "value": 300, "loot_percentage": 1},
        {"name": "Shark", "description": "Predatory sea creatures, known for their strength and aggressive nature.", "value": 300, "loot_percentage": 1},
        {"name": "Giant Shark", "description": "Huge, highly dangerous predators of the open sea.", "value": 500, "loot_percentage": 1},
        {"name": "Spiny Sleeper", "description": "A nocturnal fish that has sharp spines along its body.", "value": 70, "loot_percentage": 1},
        {"name": "Steelhead", "description": "A variant of the trout, known for its hard head and strong bite.", "value": 80, "loot_percentage": 1},
        {"name": "Sunfish", "description": "Several species of fresh and saltwater fish known for their flat, round bodies.", "value": 60, "loot_percentage": 1},
        {"name": "Knucklehead Trout", "description": "A variant of trout with a distinctive 'knuckle'-like head shape.", "value": 75, "loot_percentage": 1},
        {"name": "Szorp Trout", "description": "A rare trout species, known for its poisonous spines.", "value": 120, "loot_percentage": 1},
        {"name": "Verme", "description": "A small, colorful fish found in coral reefs.", "value": 50, "loot_percentage": 1},
        {"name": "Abyssal Angler", "description": "A deep-sea fish known for its luminescent lure.", "value": 200, "loot_percentage": 1},
        {"name": "Barracuda", "description": "A fast and aggressive predator of warm oceans.", "value": 90, "loot_percentage": 1},
        {"name": "Bluetail", "description": "A vibrant freshwater fish, popular in the aquarium trade.", "value": 40, "loot_percentage": 1},
        {"name": "Cave Carp", "description": "A blind fish found in subterranean water bodies.", "value": 80, "loot_percentage": 1},
        {"name": "Devil Ray", "description": "A large flat fish known for its long tail.", "value": 250, "loot_percentage": 1},
        {"name": "Eel", "description": "A long, snake-like fish that can deliver an electric shock.", "value": 110, "loot_percentage": 1},
        {"name": "Frostfin", "description": "A fish adapted to the coldest seas, it's scales shimmer with frost.", "value": 130, "loot_percentage": 1},
        {"name": "Giant Squid", "description": "A massive sea creature with a powerful beak.", "value": 600, "loot_percentage": 1},
        {"name": "Halibut", "description": "A flat fish found on the ocean floor.", "value": 70, "loot_percentage": 1},
        {"name": "Iridescent Icht", "description": "A fish with scales that reflect light in a dazzling array of colors.", "value": 220, "loot_percentage": 1},
        {"name": "Jade Jawfish", "description": "A green-scaled fish known for its strong jaw.", "value": 90, "loot_percentage": 1},
        {"name": "Kraken", "description": "An enormous, legendary sea creature feared by sailors.", "value": 1000, "loot_percentage": 1},
        {"name": "Leviathan", "description": "A massive, ancient sea creature of myth and legend.", "value": 1200, "loot_percentage": 1},
        {"name": "Manta Ray", "description": "A graceful swimmer known for its large pectoral fins.", "value": 100, "loot_percentage": 1},
        {"name": "Narwhal", "description": "A whale-like creature known for its long, spiral horn.", "value": 500, "loot_percentage": 1},
        {"name": "Octopus", "description": "A clever sea creature with eight tentacles.", "value": 80, "loot_percentage": 1},
        {"name": "Pearl Perch", "description": "A fish known for the pearl-like shine of its scales.", "value": 90, "loot_percentage": 1},
        {"name": "Quillfish", "description": "A small fish covered in sharp quills.", "value": 60, "loot_percentage": 1},
        {"name": "Rainbow Trout", "description": "A trout with multi-colored scales.", "value": 75, "loot_percentage": 1},
        {"name": "Sea Serpent", "description": "A massive, legendary creature of the sea.", "value": 1500, "loot_percentage": 1},
        {"name": "Tiger Shark", "description": "A large, dangerous shark known for its striped skin.", "value": 350, "loot_percentage": 1},
        {"name": "Unicorn Fish", "description": "A tropical fish known for the horn-like protrusion on its head.", "value": 110, "loot_percentage": 1},
        {"name": "Viperfish", "description": "A deep-sea fish known for its long, fang-like teeth.", "value": 200, "loot_percentage": 1},
        {"name": "Whale", "description": "A massive creature known for its songs that can be heard over great distances.", "value": 400, "loot_percentage": 1},
        {"name": "Xiphias", "description": "Also known as swordfish, recognized by its pointed bill.", "value": 300, "loot_percentage": 1},
        {"name": "Yellowfin Tuna", "description": "A fast-swimming fish known for its yellow fins and high speed.", "value": 150, "loot_percentage": 1},
        {"name": "Zebra Fish", "description": "A small freshwater fish with striking black and white stripes.", "value": 50, "loot_percentage": 1},
        {"name": "Dragonfish", "description": "A rare, mythical creature of the sea with draconic features.", "value": 1000, "loot_percentage": 1},
        {"name": "Oarfish", "description": "A long, ribbon-like fish that is rarely seen.", "value": 500, "loot_percentage": 1},
        {"name": "Glassfish", "description": "A small fish with a semi-transparent body.", "value": 40, "loot_percentage": 1},
        {"name": "Moonfish", "description": "A round, silvery fish that glows softly in the moonlight.", "value": 120, "loot_percentage": 1},
        {"name": "Starfish", "description": "A slow-moving, five-pointed creature.", "value": 20, "loot_percentage": 1},
        {"name": "Hammerhead Shark", "description": "A large shark known for its distinctive, hammer-shaped head.", "value": 330, "loot_percentage": 1},
        {"name": "Anchovy", "description": "A small, oily fish often found in large schools.", "value": 10, "loot_percentage": 1},
        {"name": "Dolphin", "description": "A highly intelligent aquatic mammal known for its playful behavior.", "value": 150, "loot_percentage": 1},
        {"name": "Lobster", "description": "A large sea creature with a hard shell and strong pincers.", "value": 100, "loot_percentage": 1},
        {"name": "Jellyfish", "description": "A soft-bodied sea creature that can sting its prey.", "value": 60, "loot_percentage": 1},
        {"name": "Stingray", "description": "A flat, diamond-shaped creature known for its long, venomous tail.", "value": 120, "loot_percentage": 1},
        {"name": "Turtle", "description": "A hard-shelled sea creature that lives a long life.", "value": 80, "loot_percentage": 1},
        {"name": "Swordfish", "description": "A fast, agile predator known for its long, sharp bill.", "value": 300, "loot_percentage": 1},
        {"name": "Clownfish", "description": "A brightly colored fish often found among sea anemones.", "value": 60, "loot_percentage": 1},
        {"name": "Pufferfish", "description": "A fish that can inflate its body into a round ball when threatened.", "value": 70, "loot_percentage": 1},
        {"name": "Old boot", "description": "It's falling apart and still smells.", "value": 0, "loot_percentage": 1},
        {"name": "Rusty Can", "description": "An old, rusted can with no label.", "value": 0, "loot_percentage": 1},
        {"name": "Tattered Cap", "description": "An old cap with a ripped peak.", "value": 0, "loot_percentage": 1},
        {"name": "Cracked Bottle", "description": "A bottle with a large crack running down its side.", "value": 0, "loot_percentage": 1},
        {"name": "Rotten Plank", "description": "A piece of wood, rotten and full of wormholes.", "value": 0, "loot_percentage": 1},
        {"name": "Broken Compass", "description": "A compass with a shattered glass and a jammed needle.", "value": 0, "loot_percentage": 1},
        {"name": "Busted Lantern", "description": "An old lantern. The glass is shattered and it's full of water.", "value": 0, "loot_percentage": 1},
        {"name": "Deflated Float", "description": "A pool float with a big tear. It's no longer useful.", "value": 0, "loot_percentage": 1},
        {"name": "Damaged Net", "description": "A fishing net with big holes and torn edges.", "value": 0, "loot_percentage": 1},
        {"name": "Dilapidated Crate", "description": "An old wooden crate. It's falling apart.", "value": 0, "loot_percentage": 1},
        {"name": "Discarded Plastic Bag", "description": "A plastic bag, torn and floating aimlessly.", "value": 0, "loot_percentage": 1},
        {"name": "Dented Canister", "description": "An old canister with a huge dent and no lid.", "value": 0, "loot_percentage": 1},
        {"name": "Soggy Cardboard", "description": "A piece of cardboard that has turned into a soggy mess.", "value": 0, "loot_percentage": 1},
        {"name": "Broken Paddle", "description": "Half of a wooden paddle. The other half is nowhere to be seen.", "value": 0, "loot_percentage": 1},
        {"name": "Old Rag", "description": "A piece of cloth, dirty and frayed at the edges.", "value": 0, "loot_percentage": 1},
        {"name": "Burnt Book", "description": "A book with burnt and water-damaged pages. Its content is lost forever.", "value": 0, "loot_percentage": 1},
        {"name": "Rusty Hook", "description": "An old, rusted hook without a line.", "value": 0, "loot_percentage": 1},
        {"name": "Leaky Bucket", "description": "A bucket with a hole at the bottom. It's useless.", "value": 0, "loot_percentage": 1},
        {"name": "Abyssal Angler", "description": "This rare, monstrous fish from the depths of the Underdark uses a luminous lure to attract prey into its gaping maw, filled with needle-like teeth. Its flesh is said to imbue the eater with temporary darkvision.", "value": 1000, "loot_percentage": 1},
        {"name": "Shadowfin Leaper", "description": "An elusive fish that swims in the currents of the Shadowfell. Its black, shimmering scales absorb light, making it almost invisible in dark waters. Consuming it is rumored to grant brief etherealness, allowing one to phase through physical barriers.", "value": 1200, "loot_percentage": 1},
        {"name": "Eldritch Eel", "description": "A serpentine creature from the Far Realm, its flesh pulses with eerie bioluminescence. Consuming it might bestow temporary telepathic abilities, but risks psychic trauma.", "value": 1500, "loot_percentage": 1},
        {"name": "Phantom Flatfish", "description": "This flat, disc-shaped fish hails from the ethereal plane. It flickers in and out of visibility in the material world.", "value": 1300, "loot_percentage": 1}
    ]
}
